snape_mss/__init__.py
snape_mss/snape.py
snape_mss-0.0.3.dist-info/METADATA
snape_mss-0.0.3.dist-info/WHEEL
snape_mss-0.0.3.dist-info/licenses/LICENSE
snape_mss-0.0.3.dist-info/RECORD
